tlcGIS/__init__.py
tlcGIS/wct.py
tlcGIS-0.0.3.dist-info/LICENSE
tlcGIS-0.0.3.dist-info/METADATA
tlcGIS-0.0.3.dist-info/WHEEL
tlcGIS-0.0.3.dist-info/top_level.txt
tlcGIS-0.0.3.dist-info/RECORD
