Metadata-Version: 2.1
Name: tlcGIS
Version: 0.0.3
Summary: gis coordinate transform tools
Author-email: Bankxi <1259564569@qq.com>
Project-URL: Homepage, https://github.com/pypa/sampleproject
Project-URL: Bug Tracker, https://github.com/pypa/sampleproject/issues
Classifier: Programming Language :: Python :: 3
Classifier: License :: OSI Approved :: MIT License
Classifier: Operating System :: OS Independent
Requires-Python: >=3.7
License-File: LICENSE
Requires-Dist: pyproj (==2.6.1.post1)
Requires-Dist: requests
